aa_tools/__init__.py
aa_tools/datalake.py
aa_tools/distances.py
aa_tools/logger.py
andreani_aa_tools-0.0.21.dist-info/LICENSE
andreani_aa_tools-0.0.21.dist-info/METADATA
andreani_aa_tools-0.0.21.dist-info/WHEEL
andreani_aa_tools-0.0.21.dist-info/top_level.txt
andreani_aa_tools-0.0.21.dist-info/RECORD
