Metadata-Version: 2.1
Name: andreani-aa-tools
Version: 0.0.21
Summary: Common functions and protocols used by the Andreani Advanced Analytics team
Home-page: https://github.com/pypa/sampleproject
Author-email: Gabriel Aranda <garanda@andreani.com>, Mariana Liu <mliu@andreani.com>, Yasmin Ojeda <yojeda@andreani.com>, Daiana Alonso <dalonso@andreani.com>, Facundo Silvestre <fsilvestre@andreani.com>, Santiago Bergman <sbergman@andreani.com>, Matías Moyano <matmoyano@andreani.com>, Giuliana Vera <gvera@andreani.com>, Eloy Chang <echang@andreani.com>, Ezequiel Brodschi <ebrodschi@andreani.com>, Sol Cari <scari@andreani.com>
License: MIT License
Project-URL: Homepage, https://github.com/eloychang/andreani_aa_tools
Project-URL: Bug Tracker, https://github.com/eloychang/andreani_aa_tools/issues
Classifier: Programming Language :: Python :: 3
Classifier: License :: OSI Approved :: MIT License
Classifier: Operating System :: OS Independent
Requires-Python: >=3.7
License-File: LICENSE
